keras_pbar/__init__.py
keras_pbar/keras_pbar.py
keras_pbar-0.0.1.dist-info/WHEEL
keras_pbar-0.0.1.dist-info/METADATA
keras_pbar-0.0.1.dist-info/RECORD
