Metadata-Version: 2.1
Name: keras_pbar
Version: 0.0.1
Summary: TQDM-like API for Keras Progressbar.
Author-email: Artem Sereda <artem.sereda.tub@gmail.com>
Maintainer-email: Artem Sereda <artem.sereda.tub@gmail.com>
Requires-Python: >=3.8
Classifier: Development Status :: 3 - Alpha
Requires-Dist: keras
Requires-Dist: tensorflow ; extra == "dev" and ( sys_platform == 'linux')
Requires-Dist: tensorflow_macos ; extra == "dev" and ( sys_platform == 'darwin')
Requires-Dist: black ; extra == "dev"
Requires-Dist: pytest ; extra == "dev"
Requires-Dist: tox ; extra == "dev"
Project-URL: Homepage, https://github.com/aaarrti/keras_pbar
Provides-Extra: dev
